[
   {
      "word": "Lor",
      "type": "PROPN",
      "citation": "⁋Lor Son Maucicio Garbora",
      "file": "192_a.xml",
      "line": 0,
      "corrected": "por",
      "probability": 0.0,
      "suggestions": [
         "Cor",
         "por",
         "Lo",
         "Los"
      ],
      "manual": false
   },
   {
      "word": "Mimas",
      "type": "NOUN",
      "citation": "⁋Mimas querido Aigo",
      "file": "192_a.xml",
      "line": 1,
      "corrected": "mas",
      "probability": 0.0,
      "suggestions": [
         "digas",
         "Mas",
         "armas",
         "fijas",
         "Tomas",
         "jamas",
         "mismas",
         "mas",
         "visas",
         "demas",
         "Armas",
         "sima"
      ],
      "manual": false
   },
   {
      "word": "Dic^t",
      "type": "NOUN",
      "citation": "Nacento 10 de Dic^t 1859",
      "file": "192_a.xml",
      "line": 2,
      "corrected": "Dic",
      "probability": 0.0,
      "suggestions": [
         "Dic"
      ],
      "manual": false
   },
   {
      "word": "aU.",
      "type": "ADJ",
      "citation": "⁋aU. del modo mas afectuoro y al miemo tiempo do",
      "file": "192_a.xml",
      "line": 4,
      "corrected": "a",
      "probability": 0.0,
      "suggestions": [
         "asi",
         "así",
         "año",
         "aun",
         "ahí",
         "ami",
         "al",
         "Un",
         "alo",
         "af",
         "aca",
         "afm",
         "aff",
         "acá",
         "am",
         "amí",
         "abe",
         "ai",
         "Ud",
         "ala",
         "a"
      ],
      "manual": false
   },
   {
      "word": "U.",
      "type": "NOUN",
      "citation": "acuerdo con el anigo celtalz hago a U. estopreso",
      "file": "192_a.xml",
      "line": 5,
      "corrected": "Ud",
      "probability": 0.0,
      "suggestions": [
         "Ud",
         "Un"
      ],
      "manual": false
   },
   {
      "word": "sabea",
      "type": "PROPN",
      "citation": "por que deceamos sabea hu paradero, como lo",
      "file": "192_a.xml",
      "line": 6,
      "corrected": "saber",
      "probability": 0.0,
      "suggestions": [
         "saber",
         "sabe"
      ],
      "manual": false
   },
   {
      "word": "hu",
      "type": "NOUN",
      "citation": "por que deceamos sabea hu paradero, como lo",
      "file": "192_a.xml",
      "line": 6,
      "corrected": "su",
      "probability": 0.0,
      "suggestions": [
         "Su",
         "eu",
         "hé",
         "su",
         "há",
         "gu",
         "tu",
         "ha",
         "Tu",
         "he"
      ],
      "manual": false
   },
   {
      "word": "dedo",
      "type": "NOUN",
      "citation": "tratan esas buenras fentes y que dedo luago nos",
      "file": "192_a.xml",
      "line": 7,
      "corrected": "dado",
      "probability": 0.0,
      "suggestions": [
         "dejo",
         "delo",
         "dado",
         "debo"
      ],
      "manual": false
   },
   {
      "word": "tudgo",
      "type": "NOUN",
      "citation": "aca alas operaceones, tudgo que tengamos avs",
      "file": "192_a.xml",
      "line": 9,
      "corrected": "tengo",
      "probability": 0.0,
      "suggestions": [
         "tengo",
         "tuvo",
         "Luego",
         "luego",
         "todo",
         "tuyo",
         "juego",
         "pudo",
         "fuego"
      ],
      "manual": false
   },
   {
      "word": "avs",
      "type": "VERB",
      "citation": "aca alas operaceones, tudgo que tengamos avs",
      "file": "192_a.xml",
      "line": 9,
      "corrected": "a",
      "probability": 0.0,
      "suggestions": [
         "asi",
         "va",
         "así",
         "Es",
         "año",
         "pais",
         "Dos",
         "s",
         "mas",
         "aviso",
         "más",
         "aun",
         "ahí",
         "ami",
         "los",
         "dos",
         "al",
         "save",
         "has",
         "años",
         "Les",
         "alo",
         "las",
         "af",
         "Tus",
         "alos",
         "aca",
         "les",
         "afm",
         "qys",
         "mes",
         "am",
         "sus",
         "aff",
         "acá",
         "res",
         "vos",
         "amí",
         "vé",
         "país",
         "ms",
         "abe",
         "ví",
         "asus",
         "nos",
         "ai",
         "amis",
         "das",
         "vá",
         "Mas",
         "tus",
         "veas",
         "ala",
         "alas",
         "Las",
         "es",
         "a",
         "Los",
         "aiso"
      ],
      "manual": false
   },
   {
      "word": "hare",
      "type": "VERB",
      "citation": "to de los progresos que hare U. por alla, me omi-",
      "file": "192_a.xml",
      "line": 10,
      "corrected": "hace",
      "probability": 0.0,
      "suggestions": [
         "haré",
         "hará"
      ],
      "manual": false
   },
   {
      "word": "U.",
      "type": "PROPN",
      "citation": "to de los progresos que hare U. por alla, me omi-",
      "file": "192_a.xml",
      "line": 10,
      "corrected": "Ud",
      "probability": 0.0,
      "suggestions": [
         "Ud",
         "Un"
      ],
      "manual": false
   },
   {
      "word": "alla",
      "type": "PROPN",
      "citation": "to de los progresos que hare U. por alla, me omi-",
      "file": "192_a.xml",
      "line": 10,
      "corrected": "halla",
      "probability": 0.0,
      "suggestions": [
         "alli",
         "alta",
         "ala",
         "halla",
         "allí",
         "ella"
      ],
      "manual": false
   },
   {
      "word": "omi-",
      "type": "VERB",
      "citation": "to de los progresos que hare U. por alla, me omi-",
      "file": "192_a.xml",
      "line": 10,
      "corrected": "mi",
      "probability": 0.0,
      "suggestions": [
         "amis",
         "ami",
         "mil",
         "mi",
         "mis"
      ],
      "manual": false
   },
   {
      "word": "eslo",
      "type": "ADJ",
      "citation": "⁋Ahora mando eslo propio por medio del lacr",
      "file": "192_a.xml",
      "line": 13,
      "corrected": "esto",
      "probability": 0.0,
      "suggestions": [
         "eso",
         "selo"
      ],
      "manual": false
   },
   {
      "word": "ec",
      "type": "PROPN",
      "citation": "que Jueupan de Caicipil que ec mí Amuigo, s",
      "file": "192_a.xml",
      "line": 14,
      "corrected": "en",
      "probability": 0.0,
      "suggestions": [
         "el",
         "eu",
         "en",
         "es",
         "er"
      ],
      "manual": false
   },
   {
      "word": "U.",
      "type": "NOUN",
      "citation": "U. disifisie a esta por medio de cepañoles debar do",
      "file": "192_a.xml",
      "line": 16,
      "corrected": "Ud",
      "probability": 0.0,
      "suggestions": [
         "Ud",
         "Un"
      ],
      "manual": false
   },
   {
      "word": "debar",
      "type": "VERB",
      "citation": "U. disifisie a esta por medio de cepañoles debar do",
      "file": "192_a.xml",
      "line": 16,
      "corrected": "dejar",
      "probability": 0.0,
      "suggestions": [
         "deban",
         "dejar",
         "deber"
      ],
      "manual": false
   },
   {
      "word": "U.",
      "type": "PROPN",
      "citation": "hucapel o de los endios amigos de que U. se ha",
      "file": "192_a.xml",
      "line": 17,
      "corrected": "Ud",
      "probability": 0.0,
      "suggestions": [
         "Ud",
         "Un"
      ],
      "manual": false
   },
   {
      "word": "ga",
      "type": "PROPN",
      "citation": "ga en esa, oenlaaeno disigirla totula da",
      "file": "192_a.xml",
      "line": 18,
      "corrected": "a",
      "probability": 0.0,
      "suggestions": [
         "ma",
         "Ya",
         "ya",
         "va",
         "la",
         "pa",
         "da",
         "gu",
         "ta",
         "ha",
         "Ha",
         "ra",
         "a"
      ],
      "manual": false
   },
   {
      "word": "Anqul",
      "type": "PROPN",
      "citation": "para mi al lacique Colima do Anqul para que",
      "file": "192_a.xml",
      "line": 19,
      "corrected": "Angol",
      "probability": 0.0,
      "suggestions": [
         "Aunque",
         "Ancud",
         "Aqui",
         "Angol"
      ],
      "manual": false
   },
   {
      "word": "triles",
      "type": "NOUN",
      "citation": "triles esta en meny buen centido para ayudar",
      "file": "192_a.xml",
      "line": 22,
      "corrected": "tres",
      "probability": 0.0,
      "suggestions": [
         "tristes",
         "tres",
         "utiles",
         "tribus"
      ],
      "manual": false
   },
   {
      "word": "meny",
      "type": "PROPN",
      "citation": "triles esta en meny buen centido para ayudar",
      "file": "192_a.xml",
      "line": 22,
      "corrected": "en",
      "probability": 0.0,
      "suggestions": [
         "me",
         "melo",
         "mand",
         "Ten",
         "mun",
         "muy",
         "mes",
         "en",
         "tend",
         "pena",
         "ley",
         "menos",
         "seno",
         "mano",
         "menor"
      ],
      "manual": false
   },
   {
      "word": "centido",
      "type": "NOUN",
      "citation": "triles esta en meny buen centido para ayudar",
      "file": "192_a.xml",
      "line": 22,
      "corrected": "tenido",
      "probability": 0.0,
      "suggestions": [
         "entodo",
         "benido",
         "venido",
         "contado"
      ],
      "manual": false
   },
   {
      "word": "alíado",
      "type": "ADJ",
      "citation": "al Govierno alíado con muches otros de im",
      "file": "192_a.xml",
      "line": 23,
      "corrected": "lado",
      "probability": 0.0,
      "suggestions": [
         "callado",
         "malvado",
         "alzados"
      ],
      "manual": false
   },
   {
      "word": "im",
      "type": "PROPN",
      "citation": "al Govierno alíado con muches otros de im",
      "file": "192_a.xml",
      "line": 23,
      "corrected": "i",
      "probability": 0.0,
      "suggestions": [
         "i",
         "in",
         "ir",
         "am",
         "mi",
         "m"
      ],
      "manual": false
   },
   {
      "word": "tecados",
      "type": "ADJ",
      "citation": "que mande con tecados al Intendento y se le",
      "file": "192_a.xml",
      "line": 25,
      "corrected": "techos",
      "probability": 0.0,
      "suggestions": [
         "dejados",
         "tapados"
      ],
      "manual": false
   },
   {
      "word": "Sor",
      "type": "PROPN",
      "citation": "⁋Sor. Coronel Dos Maunicio Daabora",
      "file": "217_a.xml",
      "line": 0,
      "corrected": "por",
      "probability": 0.0,
      "suggestions": [
         "Cor",
         "Sur",
         "por",
         "Sr",
         "Soi",
         "Por",
         "Sñr",
         "Snr"
      ],
      "manual": false
   },
   {
      "word": "byea",
      "type": "NOUN",
      "citation": "⁋byea por un endio que",
      "file": "217_a.xml",
      "line": 2,
      "corrected": "ya",
      "probability": 0.0,
      "suggestions": [
         "baca",
         "ya",
         "ber",
         "baja",
         "vea",
         "bien",
         "idea",
         "buen",
         "be",
         "crea",
         "bre",
         "beo",
         "buena",
         "ayer",
         "Sea",
         "sea"
      ],
      "manual": false
   },
   {
      "word": "fusen",
      "type": "NOUN",
      "citation": "legó de fusen se me anoliciado que un nueniera de",
      "file": "217_a.xml",
      "line": 3,
      "corrected": "quien",
      "probability": 0.0,
      "suggestions": [
         "fusil",
         "pasen",
         "buen",
         "fue",
         "fuese"
      ],
      "manual": false
   },
   {
      "word": "nar",
      "type": "PROPN",
      "citation": "⁋nar de mel indios le salio aU al encuentro adetanto",
      "file": "217_a.xml",
      "line": 4,
      "corrected": "dar",
      "probability": 0.0,
      "suggestions": [
         "Mar",
         "dar"
      ],
      "manual": false
   },
   {
      "word": "mel",
      "type": "PROPN",
      "citation": "⁋nar de mel indios le salio aU al encuentro adetanto",
      "file": "217_a.xml",
      "line": 4,
      "corrected": "el",
      "probability": 0.0,
      "suggestions": [
         "el",
         "del",
         "Del",
         "me",
         "melo",
         "mes",
         "mal"
      ],
      "manual": false
   },
   {
      "word": "salio",
      "type": "VERB",
      "citation": "⁋nar de mel indios le salio aU al encuentro adetanto",
      "file": "217_a.xml",
      "line": 4,
      "corrected": "salir",
      "probability": 0.0,
      "suggestions": [
         "salvo",
         "salgo",
         "salido",
         "salió"
      ],
      "manual": false
   },
   {
      "word": "aU",
      "type": "NOUN",
      "citation": "⁋nar de mel indios le salio aU al encuentro adetanto",
      "file": "217_a.xml",
      "line": 4,
      "corrected": "a",
      "probability": 0.0,
      "suggestions": [
         "ai",
         "al",
         "am",
         "a",
         "U"
      ],
      "manual": false
   },
   {
      "word": "Pisua",
      "type": "PROPN",
      "citation": "de Pisua y que le arrollaron aU. sutaballería y endior",
      "file": "217_a.xml",
      "line": 5,
      "corrected": "vista",
      "probability": 0.0,
      "suggestions": [
         "Tirua",
         "isla",
         "lista",
         "dista",
         "vista"
      ],
      "manual": false
   },
   {
      "word": "aU.",
      "type": "ADJ",
      "citation": "de Pisua y que le arrollaron aU. sutaballería y endior",
      "file": "217_a.xml",
      "line": 5,
      "corrected": "a",
      "probability": 0.0,
      "suggestions": [
         "asi",
         "así",
         "año",
         "aun",
         "ahí",
         "ami",
         "al",
         "Un",
         "alo",
         "af",
         "aca",
         "afm",
         "aff",
         "acá",
         "am",
         "amí",
         "abe",
         "ai",
         "Ud",
         "ala",
         "a"
      ],
      "manual": false
   },
   {
      "word": "endior",
      "type": "ADJ",
      "citation": "de Pisua y que le arrollaron aU. sutaballería y endior",
      "file": "217_a.xml",
      "line": 5,
      "corrected": "indios",
      "probability": 0.0,
      "suggestions": [
         "Indios",
         "indio",
         "indios",
         "enbio"
      ],
      "manual": false
   },
   {
      "word": "U.",
      "type": "PROPN",
      "citation": "biados, peio que la infantería de U. recharó alos que",
      "file": "217_a.xml",
      "line": 6,
      "corrected": "Ud",
      "probability": 0.0,
      "suggestions": [
         "Ud",
         "Un"
      ],
      "manual": false
   },
   {
      "word": "recharó",
      "type": "VERB",
      "citation": "biados, peio que la infantería de U. recharó alos que",
      "file": "217_a.xml",
      "line": 6,
      "corrected": "echar",
      "probability": 0.0,
      "suggestions": [
         "hechar",
         "echar"
      ],
      "manual": false
   },
   {
      "word": "ceguia",
      "type": "PROPN",
      "citation": "ccombalian y que ceguia U en penecución de ellos.",
      "file": "217_a.xml",
      "line": 7,
      "corrected": "seguir",
      "probability": 0.0,
      "suggestions": [
         "segura",
         "seguir"
      ],
      "manual": false
   },
   {
      "word": "nolicio",
      "type": "NOUN",
      "citation": "⁋Esta nolicio la transmili en el acto ala Intendencia",
      "file": "217_a.xml",
      "line": 8,
      "corrected": "oficio",
      "probability": 0.0,
      "suggestions": [
         "Policia",
         "noticia"
      ],
      "manual": false
   },
   {
      "word": "hacea",
      "type": "PROPN",
      "citation": "y me aprenero a hacea este espren con’ el ob plo",
      "file": "217_a.xml",
      "line": 9,
      "corrected": "hacer",
      "probability": 0.0,
      "suggestions": [
         "hacen",
         "hace",
         "hacia"
      ],
      "manual": false
   },
   {
      "word": "’",
      "type": "SYM",
      "citation": "y me aprenero a hacea este espren con’ el ob plo",
      "file": "217_a.xml",
      "line": 9,
      "corrected": "a",
      "probability": 0.0,
      "suggestions": [
         "M",
         "p",
         "é",
         "s",
         "B",
         "o",
         "à",
         "y",
         "b",
         "n",
         "l",
         "ó",
         "d",
         "D",
         "Q",
         "G",
         "u",
         "i",
         "N",
         "q",
         "T",
         "m",
         "Y",
         "C",
         "A",
         "P",
         "V",
         "á",
         "a",
         "r",
         "U",
         "S",
         "J"
      ],
      "manual": false
   },
   {
      "word": "plo",
      "type": "PROPN",
      "citation": "y me aprenero a hacea este espren con’ el ob plo",
      "file": "217_a.xml",
      "line": 9,
      "corrected": "lo",
      "probability": 0.0,
      "suggestions": [
         "po",
         "alo"
      ],
      "manual": false
   },
   {
      "word": "cuen-",
      "type": "PROPN",
      "citation": "lado de la tituación noliciandonos los que cuen-",
      "file": "217_a.xml",
      "line": 13,
      "corrected": "buena",
      "probability": 0.0,
      "suggestions": [
         "bueno",
         "buen",
         "Bueno",
         "buena",
         "cuenta",
         "cien",
         "cuento"
      ],
      "manual": false
   },
   {
      "word": "tas",
      "type": "PROPN",
      "citation": "tas U como amigo y quienes con los de mas va",
      "file": "217_a.xml",
      "line": 14,
      "corrected": "las",
      "probability": 0.0,
      "suggestions": [
         "das",
         "tus",
         "Mas",
         "tan",
         "tal",
         "Las",
         "ta",
         "has",
         "mas"
      ],
      "manual": false
   },
   {
      "word": "ca",
      "type": "PRON",
      "citation": "ca que ee le paeuntan como Enemigos, pues ami-",
      "file": "217_a.xml",
      "line": 15,
      "corrected": "a",
      "probability": 0.0,
      "suggestions": [
         "ma",
         "aca",
         "Ya",
         "cau",
         "va",
         "la",
         "co",
         "ya",
         "pa",
         "da",
         "ta",
         "ha",
         "Ha",
         "ra",
         "a",
         "ci"
      ],
      "manual": false
   },
   {
      "word": "ee",
      "type": "PROPN",
      "citation": "ca que ee le paeuntan como Enemigos, pues ami-",
      "file": "217_a.xml",
      "line": 15,
      "corrected": "de",
      "probability": 0.0,
      "suggestions": [
         "el",
         "pe",
         "en",
         "Te",
         "ue",
         "fe",
         "te",
         "se",
         "e",
         "ese",
         "le",
         "De",
         "me",
         "eu",
         "Me",
         "Se",
         "He",
         "ele",
         "es",
         "be",
         "he",
         "Le",
         "er"
      ],
      "manual": false
   },
   {
      "word": "Borca",
      "type": "PROPN",
      "citation": "le me adicho que los Paciques Lemunan de Borca",
      "file": "217_a.xml",
      "line": 16,
      "corrected": "poca",
      "probability": 0.0,
      "suggestions": [
         "hora",
         "cerca",
         "serca",
         "poca",
         "poría",
         "Toca",
         "Mora"
      ],
      "manual": false
   },
   {
      "word": "t",
      "type": "ADV",
      "citation": "t al de Prémaco y los hijos de Raise de Vebatruen",
      "file": "217_a.xml",
      "line": 18,
      "corrected": "a",
      "probability": 0.0,
      "suggestions": [
         "M",
         "p",
         "é",
         "ta",
         "s",
         "B",
         "o",
         "à",
         "y",
         "b",
         "n",
         "l",
         "ó",
         "d",
         "D",
         "Q",
         "tu",
         "te",
         "G",
         "u",
         "i",
         "N",
         "q",
         "T",
         "m",
         "Y",
         "C",
         "tr",
         "A",
         "P",
         "V",
         "á",
         "to",
         "ti",
         "tú",
         "a",
         "r",
         "U",
         "S",
         "J"
      ],
      "manual": false
   },
   {
      "word": "Raise",
      "type": "PROPN",
      "citation": "t al de Prémaco y los hijos de Raise de Vebatruen",
      "file": "217_a.xml",
      "line": 18,
      "corrected": "aiso",
      "probability": 0.0,
      "suggestions": [
         "pais",
         "pase",
         "darse",
         "aiso"
      ],
      "manual": false
   },
   {
      "word": "U.",
      "type": "PROPN",
      "citation": "en los que lapitancavan alos que U. a combatido",
      "file": "217_a.xml",
      "line": 19,
      "corrected": "Ud",
      "probability": 0.0,
      "suggestions": [
         "Ud",
         "Un"
      ],
      "manual": false
   },
   {
      "word": "Vuecta",
      "type": "PROPN",
      "citation": "Vuecta es",
      "file": "217_a.xml",
      "line": 20,
      "corrected": "cuenta",
      "probability": 0.0,
      "suggestions": [
         "vuelta",
         "Huerta",
         "Cuenta",
         "buelta"
      ],
      "manual": false
   },
   {
      "word": "colo",
      "type": "NOUN",
      "citation": "U dicion colo llego a Malleco enfrento de Phiquas-",
      "file": "217_a.xml",
      "line": 21,
      "corrected": "como",
      "probability": 0.0,
      "suggestions": [
         "como",
         "Solo"
      ],
      "manual": false
   },
   {
      "word": "llego",
      "type": "VERB",
      "citation": "U dicion colo llego a Malleco enfrento de Phiquas-",
      "file": "217_a.xml",
      "line": 21,
      "corrected": "luego",
      "probability": 0.0,
      "suggestions": [
         "lleno",
         "luego",
         "llega"
      ],
      "manual": false
   },
   {
      "word": "dras",
      "type": "NOUN",
      "citation": "que despues de 9 dras tuvimos que Colvennos cin",
      "file": "217_a.xml",
      "line": 22,
      "corrected": "días",
      "probability": 0.0,
      "suggestions": [
         "días",
         "das"
      ],
      "manual": false
   },
   {
      "word": "cin",
      "type": "PROPN",
      "citation": "que despues de 9 dras tuvimos que Colvennos cin",
      "file": "217_a.xml",
      "line": 22,
      "corrected": "con",
      "probability": 0.0,
      "suggestions": [
         "in",
         "ci",
         "Sin",
         "fin",
         "con",
         "sin"
      ],
      "manual": false
   },
   {
      "word": "paver",
      "type": "VERB",
      "citation": "paver tenido nenqun encuentro y se nos precen",
      "file": "217_a.xml",
      "line": 23,
      "corrected": "hacer",
      "probability": 0.0,
      "suggestions": [
         "pases",
         "haber",
         "pasen",
         "poner",
         "lacer",
         "favor",
         "saber",
         "ver",
         "pasar",
         "save",
         "pase",
         "papel",
         "placer",
         "hacer",
         "ayer",
         "padre",
         "poder"
      ],
      "manual": false
   },
   {
      "word": "precen",
      "type": "VERB",
      "citation": "paver tenido nenqun encuentro y se nos precen",
      "file": "217_a.xml",
      "line": 23,
      "corrected": "parece",
      "probability": 0.0,
      "suggestions": [
         "creyen",
         "parecer",
         "precio",
         "ofrecen",
         "parece",
         "merecen",
         "pueden",
         "precede"
      ],
      "manual": false
   },
   {
      "word": "cosían",
      "type": "VERB",
      "citation": "cosían algunos 600 indios solo por encomodan",
      "file": "217_a.xml",
      "line": 24,
      "corrected": "costa",
      "probability": 0.0,
      "suggestions": [
         "costas",
         "cosas",
         "costa"
      ],
      "manual": false
   },
   {
      "word": "ena",
      "type": "ADV",
      "citation": "poros ena diclancia en que na podiames daales",
      "file": "217_a.xml",
      "line": 25,
      "corrected": "en",
      "probability": 0.0,
      "suggestions": [
         "una",
         "Una",
         "esa",
         "en",
         "pena"
      ],
      "manual": false
   },
   {
      "word": "na",
      "type": "DET",
      "citation": "poros ena diclancia en que na podiames daales",
      "file": "217_a.xml",
      "line": 25,
      "corrected": "a",
      "probability": 0.0,
      "suggestions": [
         "va",
         "la",
         "da",
         "ta",
         "ni",
         "n",
         "nó",
         "ya",
         "Ha",
         "ma",
         "una",
         "Una",
         "no",
         "pa",
         "ha",
         "La",
         "Ya",
         "ra"
      ],
      "manual": false
   },
   {
      "word": "caes",
      "type": "VERB",
      "citation": "casa, caes que Viltalón expera contertación del",
      "file": "217_a.xml",
      "line": 26,
      "corrected": "las",
      "probability": 0.0,
      "suggestions": [
         "cabos",
         "tres",
         "cau",
         "bases",
         "cree",
         "sabes",
         "pais",
         "Pues",
         "calles",
         "caños",
         "mas",
         "creo",
         "causa",
         "has",
         "clases",
         "crea",
         "Les",
         "males",
         "casas",
         "Tales",
         "las",
         "creas",
         "cayó",
         "pases",
         "dies",
         "les",
         "caso",
         "pues",
         "cada",
         "caja",
         "mes",
         "país",
         "casa",
         "res",
         "caben",
         "cien",
         "das",
         "Mas",
         "cabo",
         "cuales",
         "casos",
         "eres",
         "veas",
         "canso",
         "pase",
         "Las",
         "es",
         "cama"
      ],
      "manual": false
   },
   {
      "word": "pará",
      "type": "VERB",
      "citation": "⁋ov^s pará emprender nueva Caimpaña mefor",
      "file": "217_a.xml",
      "line": 27,
      "corrected": "para",
      "probability": 0.0,
      "suggestions": [
         "para",
         "hará",
         "part",
         "dará"
      ],
      "manual": false
   },
   {
      "word": "vempre",
      "type": "PROPN",
      "citation": "mbinada, y vempre expesaremos lo que U. nos",
      "file": "217_a.xml",
      "line": 28,
      "corrected": "siempre",
      "probability": 0.0,
      "suggestions": [
         "ciempre",
         "Siempre",
         "verme"
      ],
      "manual": false
   },
   {
      "word": "U.",
      "type": "PROPN",
      "citation": "mbinada, y vempre expesaremos lo que U. nos",
      "file": "217_a.xml",
      "line": 28,
      "corrected": "Ud",
      "probability": 0.0,
      "suggestions": [
         "Ud",
         "Un"
      ],
      "manual": false
   },
   {
      "word": "duy",
      "type": "VERB",
      "citation": "en este miemo momento tambien duy cu",
      "file": "217_a.xml",
      "line": 29,
      "corrected": "muy",
      "probability": 0.0,
      "suggestions": [
         "Muy",
         "muy"
      ],
      "manual": false
   },
   {
      "word": "cu",
      "type": "PRON",
      "citation": "en este miemo momento tambien duy cu",
      "file": "217_a.xml",
      "line": 29,
      "corrected": "su",
      "probability": 0.0,
      "suggestions": [
         "cau",
         "Su",
         "eu",
         "ci",
         "su",
         "co",
         "gu",
         "tu",
         "Tu",
         "cui"
      ],
      "manual": false
   }
]